[
    {
      "id":1,
      "day": "شنبه",
      "leave":8,
      "leaveColor": "red",
      "working": 0,
      "workingColor": "green",
      "absence":0,
      "absenceColor": "yellow"
    },
    {
      "id":2,
      "day": "یکشنبه",
      "leave":2,
      "leaveColor": "red",
      "working": 2,
      "workingColor": "green",
      "absence":4,
      "absenceColor": "yellow"
    },
    {
      "id":3,
      "day": "دوشنبه",
      "leave":0,
      "leaveColor": "red",
      "working": 8,
      "workingColor": "green",
      "absence":0,
      "absenceColor": "yellow"
    },
    {
      "id":4,
      "day": "سه شنبه",
      "leave":8,
      "leaveColor": "red",
      "working": 0,
      "workingColor": "green",
      "absence":0,
      "absenceColor": "yellow"
    },
    {
      "id":5,
      "day": "چهارشنبه",
      "leave":1,
      "leaveColor": "red",
      "working": 6,
      "workingColor": "green",
      "absence":1,
      "absenceColor": "yellow"
    },
    {
      "id":0,
      "day": "پنج شنبه",
      "leave":0,
      "leaveColor": "red",
      "working": 3,
      "workingColor": "green",
      "absence":0,
      "absenceColor": "yellow"
    },
    {
      "id":6,
      "day": "جمعه",
      "leave":0,
      "leaveColor": "red",
      "working": 0,
      "workingColor": "green",
      "absence":0,
      "absenceColor": "yellow"
    }
  ]